<?xml version='1.0' encoding='UTF-8'?><factura version='1.1.0' id='comprobante'><infoTributaria><ambiente>2</ambiente><tipoEmision>1</tipoEmision><razonSocial>GUZMAN QUEZADA CARMEN DEL ROCIO</razonSocial><nombreComercial>PANALERA ANDREITA</nombreComercial><ruc>0702664962001</ruc><claveAcceso>0302202301070266496200120010100000014151234567817</claveAcceso><codDoc>01</codDoc><estab>001</estab><ptoEmi>010</ptoEmi><secuencial>000001415</secuencial><dirMatriz>MUNICIPALIDAD S/N  Y SAN MARTIN </dirMatriz></infoTributaria><infoFactura><fechaEmision>03/02/2023</fechaEmision><dirEstablecimiento>MUNICIPALIDAD S/N  Y SAN MARTIN </dirEstablecimiento><obligadoContabilidad>NO</obligadoContabilidad><tipoIdentificacionComprador>07</tipoIdentificacionComprador><razonSocialComprador>CONSUMIDOR FINAL</razonSocialComprador><identificacionComprador>9999999999999</identificacionComprador><totalSinImpuestos>13.79</totalSinImpuestos><totalDescuento>0</totalDescuento><totalConImpuestos><totalImpuesto><codigo>2</codigo><codigoPorcentaje>0</codigoPorcentaje><baseImponible>12.9</baseImponible><valor>0.00</valor></totalImpuesto><totalImpuesto><codigo>2</codigo><codigoPorcentaje>2</codigoPorcentaje><baseImponible>0.89</baseImponible><valor>0.11</valor></totalImpuesto></totalConImpuestos><propina>0.00</propina><importeTotal>13.9</importeTotal><moneda>DOLAR</moneda><pagos><pago><formaPago>01</formaPago><total>13.9</total></pago></pagos></infoFactura><detalles><detalle><codigoPrincipal>NID1FUN.1</codigoPrincipal><descripcion>NIDO 1 EN FUNDA DE 1 KG</descripcion><cantidad>1</cantidad><precioUnitario>12.9</precioUnitario><descuento>0</descuento><precioTotalSinImpuesto>12.9</precioTotalSinImpuesto><impuestos><impuesto><codigo>2</codigo><codigoPorcentaje>0</codigoPorcentaje><tarifa>0</tarifa><baseImponible>12.9</baseImponible><valor>0</valor></impuesto></impuestos></detalle><detalle><codigoPrincipal>IN.10</codigoPrincipal><descripcion>INTIMA NORMAL 10 UNIDADES</descripcion><cantidad>1</cantidad><precioUnitario>0.89</precioUnitario><descuento>0</descuento><precioTotalSinImpuesto>0.89</precioTotalSinImpuesto><impuestos><impuesto><codigo>2</codigo><codigoPorcentaje>2</codigoPorcentaje><tarifa>12</tarifa><baseImponible>0.89</baseImponible><valor>0.11</valor></impuesto></impuestos></detalle></detalles><infoAdicional><campoAdicional nombre='Direccion'>SN</campoAdicional><campoAdicional nombre='Telefono'>09999999</campoAdicional><campoAdicional nombre='Email'>xxxxxxxx@hotmail.com</campoAdicional><campoAdicional nombre='Observaciones'> CONTRIBUYENTE REGIMEN RIMPE              </campoAdicional></infoAdicional></factura>